Nagisa_STT/__init__.py
nagisa_stt-0.1.dist-info/METADATA
nagisa_stt-0.1.dist-info/WHEEL
nagisa_stt-0.1.dist-info/top_level.txt
nagisa_stt-0.1.dist-info/RECORD
