Metadata-Version: 2.4
Name: Nagisa_STT
Version: 0.1
Summary: This is the official Nagisa SpeechToText package created by Manvendra
Author: Manvendra Singh Patel
Author-email: techno99933@gmail.com
Requires-Dist: selenium
Requires-Dist: webdriver_manager
Dynamic: author
Dynamic: author-email
Dynamic: requires-dist
Dynamic: summary
